setup.py
simplegexf.py
simplegexf.egg-info/PKG-INFO
simplegexf.egg-info/SOURCES.txt
simplegexf.egg-info/dependency_links.txt
simplegexf.egg-info/pbr.json
simplegexf.egg-info/requires.txt
simplegexf.egg-info/top_level.txt