Metadata-Version: 1.1
Name: simplegexf
Version: 0.1.5
Summary: A simple .gexf parser/writer for python
Home-page: https://github.com/demux/simplegexf
Author: UNKNOWN
Author-email: UNKNOWN
License: MIT
Keywords: simplegexf gephi gexf
Platform: UNKNOWN
Classifier: Programming Language :: Python
Classifier: Programming Language :: Python :: 3 :: Only
Classifier: Development Status :: 3 - Alpha
Classifier: Topic :: Text Processing :: Markup :: XML
Classifier: Topic :: Scientific/Engineering :: Visualization
Classifier: License :: OSI Approved :: MIT License
